runtime/threading/__init__.py
runtime/threading/concurrent.py
runtime/threading/core/auto_clear_event.py
runtime/threading/core/continuation.py
runtime/threading/core/continue_when.py
runtime/threading/core/defaults.py
runtime/threading/core/event.py
runtime/threading/core/event_continuation.py
runtime/threading/core/helpers.py
runtime/threading/core/interrupt.py
runtime/threading/core/interrupt_exception.py
runtime/threading/core/interrupt_signal.py
runtime/threading/core/lock.py
runtime/threading/core/lock_base.py
runtime/threading/core/one_time_event.py
runtime/threading/core/semaphore.py
runtime/threading/core/threading_exception.py
runtime/threading/core/concurrent/queue.py
runtime/threading/core/parallel/background.py
runtime/threading/core/parallel/distributor.py
runtime/threading/core/parallel/for_each.py
runtime/threading/core/parallel/map.py
runtime/threading/core/parallel/parallel_exception.py
runtime/threading/core/parallel/process.py
runtime/threading/core/parallel/producer_consumer_queue.py
runtime/threading/core/parallel/producer_consumer_queue_iterator.py
runtime/threading/core/parallel/pipeline/p_context.py
runtime/threading/core/parallel/pipeline/p_filter.py
runtime/threading/core/parallel/pipeline/p_fn.py
runtime/threading/core/parallel/pipeline/p_fork.py
runtime/threading/core/parallel/pipeline/p_iterable.py
runtime/threading/core/parallel/pipeline/p_iterator.py
runtime/threading/core/parallel/pipeline/pipeline_exception.py
runtime/threading/core/tasks/aggregate_exception.py
runtime/threading/core/tasks/continuation_options.py
runtime/threading/core/tasks/helpers.py
runtime/threading/core/tasks/task.py
runtime/threading/core/tasks/task_exception.py
runtime/threading/core/tasks/task_state.py
runtime/threading/core/tasks/tasks_continuation.py
runtime/threading/core/tasks/schedulers/concurrent_task_scheduler.py
runtime/threading/core/tasks/schedulers/task_scheduler.py
runtime/threading/core/testing/debug.py
runtime_threading-0.0.2.dist-info/licenses/LICENSE
runtime_threading-0.0.2.dist-info/METADATA
runtime_threading-0.0.2.dist-info/WHEEL
runtime_threading-0.0.2.dist-info/top_level.txt
runtime_threading-0.0.2.dist-info/RECORD
